Workbook

Sheet COMPRAS
B1: EMPRESA: | E1: EMPRESA FICTICIA, C.A.
B2: R.I.F.: | E2: J-00000000-0
B3: DIRECCION: | E3: CARRERA 15 CON CALLE 38, BARQUISIMETO, LARA
B4: CONTRIBUYENTE ORDINARIO
B5: Libro de Compras (IVA) Mes AGOSTO 2026
B7: No. | C7: Fecha | D7: R.I.F. | E7: Nombre o Razon Social | F7: Tipo de Proveedor | G7: Num.Planilla Importación | H7: Fecha Decl. Aduana | I7: Num. Expediente | J7: Numero de Factura | K7: Numero de control | L7: No. Nota Débito | M7: No. Nota Crédito | N7: Tipo de Transac. | O7: No. Fact. Afect. | P7: Total Compras Incl. IVA | Q7: Alicuota % | R7: Compras sin Derecho Crédito Importación | S7: Base Importación 16% | T7: IVA Importación 16% | U7: Compras sin Derecho a Crédito (Nacional) | V7: Compras NO SUJETAS | W7: Base Alicuota General 16% | X7: I.V.A. Alicuota General 16% | Y7: Base Alicuota Reducida | Z7: I.V.A. Alicuota Reducida | AA7: Nº Comprob. Retención 75% | AB7: Fecha Comprobante | AC7: IVA Retenido (al Vendedor) | AD7: IVA Retenido (a Terceros) | AE7: Anticipo IVA (Importación)
B8: 1 | C8: 2026-08-01 | D8: J-31167790-7 | E8: Servicios Nacional Martinez, C.A. | F8: Nacional | J8: 00013300 | K8: 00013727 | N8: 01-REG | P8: 949920.22 | Q8: 16 | R8: 0 | S8: 0 | T8: 0 | U8: 0 | V8: 0 | W8: 818896.74 | X8: 131023.48 | Y8: =ROUND(W8*0.16, 2) | Z8: 0 | AA8: 202608000001 | AB8: 2026-08-01 | AC8: 98267.61 | AD8: 0 | AE8: 0
B9: 2 | C9: 2026-08-03 | D9: J-39204516-4 | E9: Grupo Centro Ramirez, S.A. | F9: Nacional | J9: 00045210 | K9: 00009821 | N9: 01-REG | P9: 350000 | Q9: 16 | R9: 0 | S9: 0 | T9: 0 | U9: 50000 | V9: 0 | W9: 258620.69 | X9: 41379.31 | Y9: =ROUND(W9*0.16, 2) | Z9: 0 | AA9: 202608000002 | AB9: 2026-08-03 | AC9: 31034.48 | AD9: 0 | AE9: 0
B10: 3 | C10: 2026-08-05 | D10: J-57030524-8 | E10: Distribuidora Centro Ramirez, C.A. | F10: Nacional | J10: 00008812 | K10: 00008812 | N10: 01-REG | P10: 180000 | Q10: 16 | R10: 0 | S10: 0 | T10: 0 | U10: 0 | V10: 0 | W10: 155172.41 | X10: 24827.59 | Y10: =ROUND(W10*0.16, 2) | Z10: 0 | AA10: 202608000003 | AB10: 2026-08-05 | AC10: 18620.69 | AD10: 0 | AE10: 0
B11: 4 | C11: 2026-08-08 | D11: J-38486360-8 | E11: Grupo Sur Perez, S.R.L. | F11: Nacional | J11: 00003411 | K11: 00003411 | N11: 01-REG | P11: 220000 | Q11: 16 | R11: 0 | S11: 0 | T11: 0 | U11: 0 | V11: 0 | W11: 189655.17 | X11: 30344.83 | Y11: =ROUND(W11*0.16, 2) | Z11: 0 | AA11: 202608000004 | AB11: 2026-08-08 | AC11: 22758.62 | AD11: 0 | AE11: 0
B12: 5 | C12: 2026-08-12 | D12: J-94122085-5 | E12: Grupo Sur Rodriguez, C.A. | F12: Nacional | J12: 00099823 | K12: 00099823 | N12: 01-REG | P12: 95000 | Q12: 16 | R12: 0 | S12: 0 | T12: 0 | U12: 0 | V12: 0 | W12: 81896.55 | X12: 13103.45 | Y12: =ROUND(W12*0.16, 2) | Z12: 0 | AA12: 202608000005 | AB12: 2026-08-12 | AC12: 9827.59 | AD12: 0 | AE12: 0
B13: 6 | C13: 2026-08-15 | D13: J002345678 | E13: SENIAT / ADUANA PRINCIPAL C-80 | F13: Importación | G13: C-80-4512 | H13: 2026-08-14 | I13: EXP-2026-881 | J13: 00000000 | K13: 00000000 | N13: 01-REG | P13: 464000 | Q13: 16 | R13: 0 | S13: 400000 | T13: 64000 | U13: 0 | V13: 0 | W13: 0 | X13: 0 | Y13: =ROUND(W13*0.16, 2) | Z13: 0 | AC13: 0 | AD13: 0 | AE13: 64000
B14: 7 | C14: 2026-08-18 | D14: J-44486413-7 | E14: Grupo Oriente Perez, S.R.L. | F14: Nacional | J14: 00001554 | K14: 00001554 | N14: 01-REG | P14: 145000 | Q14: 16 | R14: 0 | S14: 0 | T14: 0 | U14: 0 | V14: 0 | W14: 125000 | X14: 20000 | Y14: =ROUND(W14*0.16, 2) | Z14: 0 | AA14: 202608000006 | AB14: 2026-08-18 | AC14: 15000 | AD14: 0 | AE14: 0
B15: 8 | C15: 2026-08-21 | D15: J-31167790-7 | E15: Servicios Nacional Martinez, C.A. | F15: Nacional | J15: 00013450 | K15: 00013880 | N15: 01-REG | P15: 420000 | Q15: 16 | R15: 0 | S15: 0 | T15: 0 | U15: 0 | V15: 0 | W15: 362068.97 | X15: 57931.04 | Y15: =ROUND(W15*0.16, 2) | Z15: 0 | AA15: 202608000007 | AB15: 2026-08-21 | AC15: 43448.28 | AD15: 0 | AE15: 0
B16: 9 | C16: 2026-08-25 | D16: J-82130184-1 | E16: Comercializadora Omega Gomez, S.R.L. | F16: Nacional | J16: 00000789 | K16: 00000789 | N16: 01-REG | P16: 110000 | Q16: 16 | R16: 0 | S16: 0 | T16: 0 | U16: 10000 | V16: 0 | W16: 86206.9 | X16: 13793.1 | Y16: =ROUND(W16*0.16, 2) | Z16: 0 | AA16: 202608000008 | AB16: 2026-08-25 | AC16: 10344.83 | AD16: 0 | AE16: 0
B17: 10 | C17: 2026-08-28 | D17: J-36505864-8 | E17: Grupo Oriente Perez, C.A. | F17: Nacional | J17: 00000522 | K17: 00000522 | N17: 01-REG | P17: 65000 | Q17: 0 | R17: 0 | S17: 0 | T17: 0 | U17: 65000 | V17: 0 | W17: 0 | X17: 0 | Y17: =ROUND(W17*0.16, 2) | Z17: 0 | AC17: 0 | AD17: 0 | AE17: 0
E18: TOTAL GENERAL | P18: =SUM(P8:P17) | R18: =SUM(R8:R17) | S18: =SUM(S8:S17) | T18: =SUM(T8:T17) | U18: =SUM(U8:U17) | V18: =SUM(V8:V17) | W18: =SUM(W8:W17) | X18: =SUM(X8:X17) | Y18: =SUM(Y8:Y17) | Z18: =SUM(Z8:Z17) | AC18: =SUM(AC8:AC17) | AD18: =SUM(AD8:AD17) | AE18: =SUM(AE8:AE17)
D21: J-37151256-0 | E21: Comercializadora Alfa Rodriguez, S.A.
D22: J-34484719-4 | E22: Servicios Lara Martinez, S.A. | F22: BASE IMPONIBLE | I22: CRÉDITOS FISCALES
D23: J-56586010-1 | E23: Grupo Global Perez, C.A. | F23: =U18 | I23: 0
D24: J-69512872-9 | E24: Servicios Lara Lopez, C.A. | F24: =V18 | I24: 0
D25: J-74843890-6 | E25: Distribuidora Centro Sanchez, S.A. | F25: =S18 | I25: =T18
D26: J-69411367-6 | E26: Servicios Omega Ramirez, C.A. | F26: =W18 | I26: =X18
D27: J-60974141-8 | E27: Servicios Centro Lopez, S.R.L. | F27: =F23+F24+F25+F26 | I27: =I23+I24+I25+I26

Sheet VENTAS
B5: EMPRESA: | E5: EMPRESA FICTICIA, C.A.
B6: R.I.F.: | E6: R.I.F.: J-00000000-0
B7: DIRECCION: | D7: CARRERA 15 CON CALLE 38
B8: CONTRIBUYENTE ORDINARIO
B9: Libro de Ventas (IVA) Mes de | E9: AGOSTO 2026
B11: Oper. No. | C11: Fecha de la Factura | D11: R.I.F | E11: Nombre o Razon Social | F11: No. Declaracion Exportación | G11: Maquina Fiscal | H11: Numero Factura / Reporte Z | I11: FACTURA | J11: Numero de Control | K11: No de Nota de Debito | L11: No de Nota de Credito | M11: Tipo de transac. | N11: No de Factura Afectada | O11: Total Ventas incluyendo el IVA | P11: Ventas No sujetas | Q11: Ventas no gravadas (No Contrib) | R11: Base Imponible (No Contrib) | S11: % alicuota | T11: Impuesto IVA (No Contrib) | U11: Ventas no gravadas (Contrib) | V11: Base Imponible (Contrib) | W11: % alicuota | X11: Impuesto IVA (Contrib) | Y11: Nº Comprob. Retención 75% IVA | Z11: Fecha del Comprobante | AA11: Iva Retenido (por comprador) | AB11: Iva retenido percibido
B12: 1 | C12: 2026-08-01 | D12: J-24999770-5 | E12: Corporacion Nacional Sanchez, S.R.L. | H12: 000134 | I12: 000134 | J12: 000134 | M12: 01-REG | O12: 89532.74 | P12: 0 | Q12: 0 | R12: 0 | S12: 16 | T12: 0 | U12: 0 | V12: 77183.4 | W12: 16 | X12: 12349.34 | Y12: 202608000101 | Z12: 2026-08-01 | AA12: 9262.01 | AB12: 3087.33
B13: 2 | C13: 2026-08-01 | D13: V-26920712 | E13: Sofia Rodriguez (Persona Natural) | H13: 000135 | I13: 000135 | J13: 000135 | M13: 01-REG | O13: 119378.24 | P13: 0 | Q13: 0 | R13: 102912.28 | S13: 16 | T13: 16465.96 | U13: 0 | V13: 0 | W13: 16 | X13: 0 | AA13: 0 | AB13: 0
B14: 3 | C14: 2026-08-02 | D14: J-69532017-9 | E14: Grupo Omega Lopez, C.A. | H14: 000136 | I14: 000136 | J14: 000136 | M14: 01-REG | O14: 132690.7 | P14: 0 | Q14: 0 | R14: 0 | S14: 16 | T14: 0 | U14: 0 | V14: 114388.53 | W14: 16 | X14: 18302.16 | Y14: 202608000102 | Z14: 2026-08-02 | AA14: 13726.62 | AB14: 4575.54
B15: 4 | C15: 2026-08-08 | D15: J-22320599-3 | E15: Distribuidora Beta Garcia, C.A. | H15: 000137 | I15: 000137 | J15: 000137 | M15: 01-REG | O15: 30411.39 | P15: 0 | Q15: 0 | R15: 0 | S15: 16 | T15: 0 | U15: 0 | V15: 26216.72 | W15: 16 | X15: 4194.68 | Y15: 202608000103 | Z15: 2026-08-08 | AA15: 3146.01 | AB15: 1048.67
B16: 5 | C16: 2026-08-13 | D16: J-99300189-1 | E16: Comercializadora Sur Gomez, S.R.L. | H16: 000138 | I16: 000138 | J16: 000138 | M16: 01-REG | O16: 26082.43 | P16: 0 | Q16: 0 | R16: 0 | S16: 16 | T16: 0 | U16: 0 | V16: 22484.85 | W16: 16 | X16: 3597.58 | Y16: 202608000104 | Z16: 2026-08-13 | AA16: 2698.18 | AB16: 899.39
B17: 6 | C17: 2026-08-16 | E17: *** FACTURA ANULADA *** | H17: 000139 | I17: 000139 | J17: 000139 | M17: 03-ANU | O17: 0 | P17: 0 | Q17: 0 | R17: 0 | S17: 16 | T17: 0 | U17: 0 | V17: 0 | W17: 16 | X17: 0 | AA17: 0 | AB17: 0
B18: 7 | C18: 2026-08-16 | D18: J-69532017-9 | E18: Grupo Omega Lopez, C.A. | H18: 000140 | I18: 000140 | J18: 000140 | M18: 01-REG | O18: 137441.04 | P18: 0 | Q18: 0 | R18: 118483.66 | S18: 16 | T18: 18957.39 | U18: 0 | V18: 0 | W18: 16 | X18: 0 | AA18: 0 | AB18: 0
B19: 8 | C19: 2026-08-18 | D19: V-26920712 | E19: Sofia Rodriguez (Persona Natural) | H19: 000141 | I19: 000141 | J19: 000141 | M19: 01-REG | O19: 136530.95 | P19: 0 | Q19: 0 | R19: 117699.09 | S19: 16 | T19: 18831.85 | U19: 0 | V19: 0 | W19: 16 | X19: 0 | AA19: 0 | AB19: 0
B20: 9 | C20: 2026-08-23 | D20: J-87440536-9 | E20: Comercializadora Global Gonzalez, C.A. | H20: 000142 | I20: 000142 | J20: 000142 | M20: 01-REG | O20: 9221.88 | P20: 0 | Q20: 0 | R20: 0 | S20: 16 | T20: 0 | U20: 0 | V20: 7949.9 | W20: 16 | X20: 1271.98 | Y20: 202608000105 | Z20: 2026-08-23 | AA20: 953.99 | AB20: 317.99
B21: 10 | C21: 2026-08-27 | D21: J-35762696-6 | E21: Servicios Sur Perez, S.A. | H21: 000143 | I21: 000143 | J21: 000143 | M21: 01-REG | O21: 98500 | P21: 0 | Q21: 0 | R21: 0 | S21: 16 | T21: 0 | U21: 12500 | V21: 74137.93 | W21: 16 | X21: 11862.07 | Y21: 202608000106 | Z21: 2026-08-27 | AA21: 8896.55 | AB21: 2965.52
E22: TOTALES | O22: =SUM(O12:O21) | P22: =SUM(P12:P21) | Q22: =SUM(Q12:Q21) | R22: =SUM(R12:R21) | T22: =SUM(T12:T21) | U22: =SUM(U12:U21) | V22: =SUM(V12:V21) | X22: =SUM(X12:X21) | AA22: =SUM(AA12:AA21) | AB22: =SUM(AB12:AB21)
D25: J-10710906-1 | E25: Servicios Alfa Garcia, C.A.
D26: J-34484719-4 | E26: Servicios Lara Martinez, S.A. | F26: CÓDIGO | H26: BASE IMPONIBLE | K26: DÉBITOS FISCALES
D27: V-17924660 | E27: Laura Gonzalez (Persona Natural) | F27: 40 | H27: =Q22+U22 | K27: 0
D28: V-29275264 | E28: Sofia Garcia (Persona Natural) | F28: 40 | H28: =P22 | K28: 0
D29: V-27562928 | E29: Carlos Ramirez (Persona Natural) | F29: 41 | H29: 0 | K29: 0
D30: V-25620802 | E30: Juan Sanchez (Persona Natural) | F30: 42 | H30: =R22+V22 | K30: =T22+X22
D31: J-81815350-0 | E31: Servicios Beta Martinez, S.A. | F31: 46 | H31: =H27+H28+H29+H30 | K31: =K27+K28+K29+K30
D32: J-21964592-7 | E32: Distribuidora Alfa Martinez, S.A. | F32: 48 | H32: 0 | K32: 0
D33: J-91315590-0 | E33: Corporacion Beta Perez, S.R.L. | F33: 49 | H33: =H31 | K33: =K31+K32
D34: J-43238457-1 | E34: Corporacion Omega Gomez, S.A. | F34: 66 | K34: =AA22

Sheet PLANILLA
A1: FORMA IVA 99030
A2: DECLARACION Y PAGO DEL IMPUESTO AL VALOR AGREGADO
A3: PLANILLA Nº 20 - SENIAT
A4: RIF DE LA EMPRESA: J-00000000-0
A5: MES A DECLARAR: MES DE AGOSTO 2026
A7: Ítem | B7: Concepto / Descripción | C7: Código Base | D7: BASE IMPONIBLE | E7: Código Impuesto | F7: DÉBITO / CRÉDITO FISCAL
A8: DEBITOS FISCALES (VENTAS)
A9: 1 | B9: Ventas internas no gravadas | C9: 40 | D9: =VENTAS!H27
A10: 2 | B10: Ventas de exportación | C10: 41 | D10: 0
A11: 3 | B11: Ventas internas gravadas por alícuota general 16% | C11: 42 | D11: =VENTAS!H30 | E11: 43 | F11: =VENTAS!K30
A12: 6 | B12: Total ventas y débitos fiscales para efectos de determinación | C12: 46 | D12: =D9+D10+D11 | E12: 47 | F12: =F11
A13: 7 | B13: Ajuste a los débitos fiscales de períodos anteriores | E13: 48 | F13: 0
A14: 9 | B14: Total débitos fiscales | E14: 49 | F14: =F12+F13
A15: CREDITOS FISCALES (COMPRAS)
A16: 10 | B16: Compras no gravadas y/o sin derecho a crédito fiscal | C16: 30 | D16: =COMPRAS!F23
A17: 11 | B17: Importación gravadas por alícuota general | C17: 31 | D17: =COMPRAS!F25 | E17: 32 | F17: =COMPRAS!I25
A18: 14 | B18: Compras internas gravadas solo por alícuota general 16% | C18: 33 | D18: =COMPRAS!F26 | E18: 34 | F18: =COMPRAS!I26
A19: 17 | B19: Total compras y créditos fiscales del Período | C19: 35 | D19: =D16+D17+D18 | E19: 36 | F19: =F17+F18
A20: 18 | B20: Créditos fiscales deducibles | E20: 70 | F20: =F19
A21: 20 | B21: Total créditos fiscales deducibles | E21: 71 | F21: =F20
A22: 21 | B22: Excedente créditos fiscales del mes anterior | E22: 20 | F22: 125000
A23: 26 | B23: Total Créditos Fiscales | E23: 39 | F23: =F21+F22
A24: AUTOLIQUIDACION DEL IMPUESTO
A25: 27 | B25: TOTAL IMPUESTO DEL PERÍODO (Si Débitos > Créditos) | E25: 53 | F25: =IF(F14>F23, F14-F23, 0)
A26: 28 | B26: Excedente crédito fiscal para el mes siguiente (Si Créditos > Débitos) | E26: 60 | F26: =IF(F23>F14, F23-F14, 0)
A27: 33 | B27: Retenciones acumuladas por descontar (Meses anteriores) | C27: 54 | D27: 45000
A28: 34 | B28: Retenciones del período (Recibidas de Clientes) | C28: 66 | D28: =VENTAS!K34
A29: 37 | B29: Total Retenciones Disponibles | C29: 74 | D29: =D27+D28
A30: 38 | B30: Retenciones soportadas y descontadas en esta declaración | E30: 55 | F30: =MIN(F25, D29)
A31: 39 | B31: Saldo de retenciones IVA no aplicado (Excedente para el mes siguiente) | C31: 67 | D31: =D29-F30
A32: 48 | B32: TOTAL A PAGAR DE IVA EN ESTE PERÍODO | E32: 90 | F32: =MAX(0, F25-F30)
